setup.cfg
setup.py
pyblockMesh.egg-info/PKG-INFO
pyblockMesh.egg-info/SOURCES.txt
pyblockMesh.egg-info/dependency_links.txt
pyblockMesh.egg-info/not-zip-safe
pyblockMesh.egg-info/top_level.txt
pyblockmesh/__init__.py
pyblockmesh/edge.py
pyblockmesh/face.py
pyblockmesh/hexahedron.py
pyblockmesh/vertex.py