Metadata-Version: 1.2
Name: pyblockMesh
Version: 0.0.2
Summary: Python wrapper around blockMeshDict creation
Home-page: https://github.com/grokkingStuff/pyblockmesh
Author: Vishakh Kumar
Author-email: grokkingStuff@gmail.com
License: MIT License
Keywords: blockmesh blockmeshdict openfoam pyfoam
Platform: UNKNOWN
Classifier: Development Status :: 3 - Alpha
Classifier: Intended Audience :: Developers
Classifier: License :: OSI Approved :: MIT License
Classifier: Programming Language :: Python :: 3
Classifier: Programming Language :: Python :: 3.2
Classifier: Programming Language :: Python :: 3.2
Classifier: Programming Language :: Python :: 3.3
Classifier: Programming Language :: Python :: 3.4
Requires-Python: >=3
